{"id": "MlzTET_8SQg", "title": "Mot\u00f6rhead \u2013 Overkill (Official Video)", "formats": [{"asr": 48000, "filesize": 1740711, "format_id": "249", "format_note": "tiny", "fps": null, "height": null, "quality": 0, "tbr": 43.896, "url": "https://rr5---sn-0opoxu-ihv6.googlevideo.com/videoplayback?expire=1670795486&ei=fvyVY9KCFsKXkway_LHwCQ&ip=189.173.225.87&id=o-ABmi8SIQqP8x1u2FH9kwFA74M54JlyN7Di6pYTfCz2sD&itag=249&source=youtube&requiressl=yes&mh=YF&mm=31%2C29&mn=sn-0opoxu-ihv6%2Csn-q4flrnlz&ms=au%2Crdu&mv=m&mvi=5&pl=24&initcwndbps=861250&vprv=1&mime=audio%2Fwebm&ns=ajrLFqX9024sAm2XfGBg_0MJ&gir=yes&clen=1740711&dur=317.241&lmt=1576356536960230&mt=1670773517&fvip=2&keepalive=yes&fexp=24001373%2C24007246&c=WEB&txp=5531432&n=p7s-ahxPTjp8JeEob&sparams=expire%2Cei%2Cip%2Cid%2Citag%2Csource%2Crequiressl%2Cvprv%2Cmime%2Cns%2Cgir%2Cclen%2Cdur%2Clmt&lsparams=mh%2Cmm%2Cmn%2Cms%2Cmv%2Cmvi%2Cpl%2Cinitcwndbps&lsig=AG3C_xAwRAIgaKwXqwVjAMPjAJRDAxX9lwyqPddE_Oo6SYqW8mcD66ICIHTQ_YOycONO6TXYni1J1gaibFkS8zuxgehj_sbC1Wcz&sig=AOq0QJ8wRQIgFYLY1MaA1H6LzZ8YsxE1cLFR_GMfwEnPoieoniOiBOQCIQD2aRM-4ThF97vX3bYu5tN4HTxtNnmDLpOEtpLwGFTgkQ==", "width": null, "ext": "webm", "vcodec": "none", "acodec": "opus", "abr": 43.896, "downloader_options": {"http_chunk_size": 10485760}, "container": "webm_dash", "format": "249 - audio only (tiny)", "protocol": "https", "http_headers": {"User-Agent": "Mozilla/5.0 (Windows NT 10.0; Win64; x64) AppleWebKit/537.36 (KHTML, like Gecko) Chrome/74.0.3729.92 Safari/537.36", "Accept-Charset": "ISO-8859-1,utf-8;q=0.7,*;q=0.7", "Accept": "text/html,application/xhtml+xml,application/xml;q=0.9,*/*;q=0.8", "Accept-Encoding": "gzip, deflate", "Accept-Language": "en-us,en;q=0.5"}}, {"asr": 48000, "filesize": 2315314, "format_id": "250", "format_note": "tiny", "fps": null, "height": null, "quality": 0, "tbr": 58.386, "url": "https://rr5---sn-0opoxu-ihv6.googlevideo.com/videoplayback?expire=1670795486&ei=fvyVY9KCFsKXkway_LHwCQ&ip=189.173.225.87&id=o-ABmi8SIQqP8x1u2FH9kwFA74M54JlyN7Di6pYTfCz2sD&itag=250&source=youtube&requiressl=yes&mh=YF&mm=31%2C29&mn=sn-0opoxu-ihv6%2Csn-q4flrnlz&ms=au%2Crdu&mv=m&mvi=5&pl=24&initcwndbps=861250&vprv=1&mime=audio%2Fwebm&ns=ajrLFqX9024sAm2XfGBg_0MJ&gir=yes&clen=2315314&dur=317.241&lmt=1576356544508423&mt=1670773517&fvip=2&keepalive=yes&fexp=24001373%2C24007246&c=WEB&txp=5531432&n=p7s-ahxPTjp8JeEob&sparams=expire%2Cei%2Cip%2Cid%2Citag%2Csource%2Crequiressl%2Cvprv%2Cmime%2Cns%2Cgir%2Cclen%2Cdur%2Clmt&lsparams=mh%2Cmm%2Cmn%2Cms%2Cmv%2Cmvi%2Cpl%2Cinitcwndbps&lsig=AG3C_xAwRQIhAPXONqQ-nZ4EDMDZ-AYXRQWNt1oEiBy-h3U4xto8351JAiAdPpRjtQYxkeIVHhz-fkJEo6E0n1yBd4UqS86TWqM75A%3D%3D&sig=AOq0QJ8wRQIhALXd2phDDefkHGT5lPXd4PFlBaSdvB_MiLnh2lM8mxXtAiA36ADUUV8g9KCkPyomSfMOyF0BBQRoJkNVDGJpOzz51A==", "width": null, "ext": "webm", "vcodec": "none", "acodec": "opus", "abr": 58.386, "downloader_options": {"http_chunk_size": 10485760}, "container": "webm_dash", "format": "250 - audio only (tiny)", "protocol": "https", "http_headers": {"User-Agent": "Mozilla/5.0 (Windows NT 10.0; Win64; x64) AppleWebKit/537.36 (KHTML, like Gecko) Chrome/74.0.3729.92 Safari/537.36", "Accept-Charset": "ISO-8859-1,utf-8;q=0.7,*;q=0.7", "Accept": "text/html,application/xhtml+xml,application/xml;q=0.9,*/*;q=0.8", "Accept-Encoding": "gzip, deflate", "Accept-Language": "en-us,en;q=0.5"}}, {"asr": 48000, "filesize": 4688283, "format_id": "251", "format_note": "tiny", "fps": null, "height": null, "quality": 0, "tbr": 118.226, "url": "https://rr5---sn-0opoxu-ihv6.googlevideo.com/videoplayback?expire=1670795486&ei=fvyVY9KCFsKXkway_LHwCQ&ip=189.173.225.87&id=o-ABmi8SIQqP8x1u2FH9kwFA74M54JlyN7Di6pYTfCz2sD&itag=251&source=youtube&requiressl=yes&mh=YF&mm=31%2C29&mn=sn-0opoxu-ihv6%2Csn-q4flrnlz&ms=au%2Crdu&mv=m&mvi=5&pl=24&initcwndbps=861250&vprv=1&mime=audio%2Fwebm&ns=ajrLFqX9024sAm2XfGBg_0MJ&gir=yes&clen=4688283&dur=317.241&lmt=1576356544773842&mt=1670773517&fvip=2&keepalive=yes&fexp=24001373%2C24007246&c=WEB&txp=5531432&n=p7s-ahxPTjp8JeEob&sparams=expire%2Cei%2Cip%2Cid%2Citag%2Csource%2Crequiressl%2Cvprv%2Cmime%2Cns%2Cgir%2Cclen%2Cdur%2Clmt&lsparams=mh%2Cmm%2Cmn%2Cms%2Cmv%2Cmvi%2Cpl%2Cinitcwndbps&lsig=AG3C_xAwRAIgaUPK7T1kivVO20H9zd0v93g-Syi4uwFE2jx3kiEX9jkCIFugDdqorIsZzHjmrdT_1zOY7yAtb6T0rZLNPca9jzBM&sig=AOq0QJ8wRgIhAOMKFNk7GKXNk1z9rUWZYEErZEyh4WOY7okWpLvpnUQWAiEAofSrvP6i5Y_C9kNp5u3K8vKJIFYJUxHAlaMIT2TcUnU=", "width": null, "ext": "webm", "vcodec": "none", "acodec": "opus", "abr": 118.226, "downloader_options": {"http_chunk_size": 10485760}, "container": "webm_dash", "format": "251 - audio only (tiny)", "protocol": "https", "http_headers": {"User-Agent": "Mozilla/5.0 (Windows NT 10.0; Win64; x64) AppleWebKit/537.36 (KHTML, like Gecko) Chrome/74.0.3729.92 Safari/537.36", "Accept-Charset": "ISO-8859-1,utf-8;q=0.7,*;q=0.7", "Accept": "text/html,application/xhtml+xml,application/xml;q=0.9,*/*;q=0.8", "Accept-Encoding": "gzip, deflate", "Accept-Language": "en-us,en;q=0.5"}}, {"asr": 44100, "filesize": 5135471, "format_id": "140", "format_note": "tiny", "fps": null, "height": null, "quality": 0, "tbr": 129.488, "url": "https://rr5---sn-0opoxu-ihv6.googlevideo.com/videoplayback?expire=1670795486&ei=fvyVY9KCFsKXkway_LHwCQ&ip=189.173.225.87&id=o-ABmi8SIQqP8x1u2FH9kwFA74M54JlyN7Di6pYTfCz2sD&itag=140&source=youtube&requiressl=yes&mh=YF&mm=31%2C29&mn=sn-0opoxu-ihv6%2Csn-q4flrnlz&ms=au%2Crdu&mv=m&mvi=5&pl=24&initcwndbps=861250&vprv=1&mime=audio%2Fmp4&ns=ajrLFqX9024sAm2XfGBg_0MJ&gir=yes&clen=5135471&dur=317.277&lmt=1576356549915857&mt=1670773517&fvip=2&keepalive=yes&fexp=24001373%2C24007246&c=WEB&txp=5531432&n=p7s-ahxPTjp8JeEob&sparams=expire%2Cei%2Cip%2Cid%2Citag%2Csource%2Crequiressl%2Cvprv%2Cmime%2Cns%2Cgir%2Cclen%2Cdur%2Clmt&lsparams=mh%2Cmm%2Cmn%2Cms%2Cmv%2Cmvi%2Cpl%2Cinitcwndbps&lsig=AG3C_xAwRgIhAP8cVh44gpLSXY0qSt0BunWc3l6q-s0PA_JxvDy_Vdm6AiEAwTZIHV5sGNVetyc6Ypnx_O1OF7QAhUWKO5D5hXijQmw%3D&sig=AOq0QJ8wRQIgEPlpoG1e20OMB4bnTHzC1V_ErRCsD-FtQje_1yW4JOoCIQCY_Z8Zzhucuyimv0TgchTusbvDPRdvFEfNdGjOeRy7Ag==", "width": null, "ext": "m4a", "vcodec": "none", "acodec": "mp4a.40.2", "abr": 129.488, "downloader_options": {"http_chunk_size": 10485760}, "container": "m4a_dash", "format": "140 - audio only (tiny)", "protocol": "https", "http_headers": {"User-Agent": "Mozilla/5.0 (Windows NT 10.0; Win64; x64) AppleWebKit/537.36 (KHTML, like Gecko) Chrome/74.0.3729.92 Safari/537.36", "Accept-Charset": "ISO-8859-1,utf-8;q=0.7,*;q=0.7", "Accept": "text/html,application/xhtml+xml,application/xml;q=0.9,*/*;q=0.8", "Accept-Encoding": "gzip, deflate", "Accept-Language": "en-us,en;q=0.5"}}, {"asr": null, "filesize": 2160928, "format_id": "394", "format_note": "144p", "fps": 30, "height": 144, "quality": 0, "tbr": 54.497, "url": "https://rr5---sn-0opoxu-ihv6.googlevideo.com/videoplayback?expire=1670795486&ei=fvyVY9KCFsKXkway_LHwCQ&ip=189.173.225.87&id=o-ABmi8SIQqP8x1u2FH9kwFA74M54JlyN7Di6pYTfCz2sD&itag=394&aitags=133%2C134%2C135%2C160%2C242%2C243%2C244%2C278%2C394%2C395%2C396%2C397&source=youtube&requiressl=yes&mh=YF&mm=31%2C29&mn=sn-0opoxu-ihv6%2Csn-q4flrnlz&ms=au%2Crdu&mv=m&mvi=5&pl=24&initcwndbps=861250&vprv=1&mime=video%2Fmp4&ns=ajrLFqX9024sAm2XfGBg_0MJ&gir=yes&clen=2160928&dur=317.216&lmt=1627506515314372&mt=1670773517&fvip=2&keepalive=yes&fexp=24001373%2C24007246&c=WEB&txp=5532434&n=p7s-ahxPTjp8JeEob&sparams=expire%2Cei%2Cip%2Cid%2Caitags%2Csource%2Crequiressl%2Cvprv%2Cmime%2Cns%2Cgir%2Cclen%2Cdur%2Clmt&lsparams=mh%2Cmm%2Cmn%2Cms%2Cmv%2Cmvi%2Cpl%2Cinitcwndbps&lsig=AG3C_xAwRQIhALc3EBpLqaFKNg76e2Dx-WFbo2HRaEKBFLV1_54onfiDAiA336NGtZLqC6h80WxozeEG0FD7jHzdW7ntOeIiRJRkQA%3D%3D&sig=AOq0QJ8wRQIhAM2e3utuBtJ-G3-FuapDMYPdwwh8sXGvgJECMnfPLjq7AiB8E3harRlKP3D_ZE7gng59fg2RtkL9o98IwkbNRsphOg==", "width": 192, "ext": "mp4", "vcodec": "av01.0.00M.08.0.110.06.01.06.0", "acodec": "none", "vbr": 54.497, "downloader_options": {"http_chunk_size": 10485760}, "container": "mp4_dash", "format": "394 - 192x144 (144p)", "protocol": "https", "http_headers": {"User-Agent": "Mozilla/5.0 (Windows NT 10.0; Win64; x64) AppleWebKit/537.36 (KHTML, like Gecko) Chrome/74.0.3729.92 Safari/537.36", "Accept-Charset": "ISO-8859-1,utf-8;q=0.7,*;q=0.7", "Accept": "text/html,application/xhtml+xml,application/xml;q=0.9,*/*;q=0.8", "Accept-Encoding": "gzip, deflate", "Accept-Language": "en-us,en;q=0.5"}}, {"asr": null, "filesize": 2638849, "format_id": "160", "format_note": "144p", "fps": 30, "height": 144, "quality": 0, "tbr": 66.55, "url": "https://rr5---sn-0opoxu-ihv6.googlevideo.com/videoplayback?expire=1670795486&ei=fvyVY9KCFsKXkway_LHwCQ&ip=189.173.225.87&id=o-ABmi8SIQqP8x1u2FH9kwFA74M54JlyN7Di6pYTfCz2sD&itag=160&aitags=133%2C134%2C135%2C160%2C242%2C243%2C244%2C278%2C394%2C395%2C396%2C397&source=youtube&requiressl=yes&mh=YF&mm=31%2C29&mn=sn-0opoxu-ihv6%2Csn-q4flrnlz&ms=au%2Crdu&mv=m&mvi=5&pl=24&initcwndbps=861250&vprv=1&mime=video%2Fmp4&ns=ajrLFqX9024sAm2XfGBg_0MJ&gir=yes&clen=2638849&dur=317.216&lmt=1576357888874404&mt=1670773517&fvip=2&keepalive=yes&fexp=24001373%2C24007246&c=WEB&txp=5532432&n=p7s-ahxPTjp8JeEob&sparams=expire%2Cei%2Cip%2Cid%2Caitags%2Csource%2Crequiressl%2Cvprv%2Cmime%2Cns%2Cgir%2Cclen%2Cdur%2Clmt&lsparams=mh%2Cmm%2Cmn%2Cms%2Cmv%2Cmvi%2Cpl%2Cinitcwndbps&lsig=AG3C_xAwRgIhAJJGcVsShUVRwqpnDSjJwn7l1nYV7NeG1IcDRNzlxoJJAiEAtNp7Vj5wu_Sh1ZJEwGn4ugIM0zt1nnGk-BhCc3AoJJc%3D&sig=AOq0QJ8wRAIgQ324K7kY2sFqZ1OvYJymZivQh0K1UZuP06jse0sSNdoCIB-S0TA5Ykhcizjxd_ZV8rphj89svTGiECYqAD02ZXEf", "width": 192, "ext": "mp4", "vcodec": "avc1.4d400c", "acodec": "none", "vbr": 66.55, "downloader_options": {"http_chunk_size": 10485760}, "container": "mp4_dash", "format": "160 - 192x144 (144p)", "protocol": "https", "http_headers": {"User-Agent": "Mozilla/5.0 (Windows NT 10.0; Win64; x64) AppleWebKit/537.36 (KHTML, like Gecko) Chrome/74.0.3729.92 Safari/537.36", "Accept-Charset": "ISO-8859-1,utf-8;q=0.7,*;q=0.7", "Accept": "text/html,application/xhtml+xml,application/xml;q=0.9,*/*;q=0.8", "Accept-Encoding": "gzip, deflate", "Accept-Language": "en-us,en;q=0.5"}}, {"asr": null, "filesize": 2823196, "format_id": "278", "format_note": "144p", "fps": 30, "height": 144, "quality": 0, "tbr": 71.199, "url": "https://rr5---sn-0opoxu-ihv6.googlevideo.com/videoplayback?expire=1670795486&ei=fvyVY9KCFsKXkway_LHwCQ&ip=189.173.225.87&id=o-ABmi8SIQqP8x1u2FH9kwFA74M54JlyN7Di6pYTfCz2sD&itag=278&aitags=133%2C134%2C135%2C160%2C242%2C243%2C244%2C278%2C394%2C395%2C396%2C397&source=youtube&requiressl=yes&mh=YF&mm=31%2C29&mn=sn-0opoxu-ihv6%2Csn-q4flrnlz&ms=au%2Crdu&mv=m&mvi=5&pl=24&initcwndbps=861250&vprv=1&mime=video%2Fwebm&ns=ajrLFqX9024sAm2XfGBg_0MJ&gir=yes&clen=2823196&dur=317.216&lmt=1576358072853938&mt=1670773517&fvip=2&keepalive=yes&fexp=24001373%2C24007246&c=WEB&txp=5531432&n=p7s-ahxPTjp8JeEob&sparams=expire%2Cei%2Cip%2Cid%2Caitags%2Csource%2Crequiressl%2Cvprv%2Cmime%2Cns%2Cgir%2Cclen%2Cdur%2Clmt&lsparams=mh%2Cmm%2Cmn%2Cms%2Cmv%2Cmvi%2Cpl%2Cinitcwndbps&lsig=AG3C_xAwRQIgTeCz6rGkE5J9Da2Kmj99LTmfTNUj6dljS2Z6dP5JjzACIQDk6fJRe_tLMCDMTiDbkuFR1OZvji5cDJGYOEguNBSz-g%3D%3D&sig=AOq0QJ8wRAIgVWJYYyPhx-uvekZZXNidp6fSPOWhoaEsCmBkOAKDzC4CIEYS84HbdwNYTjvKJks2cvPDp269wRtx_QsR3MIZnxnK", "width": 192, "ext": "webm", "vcodec": "vp9", "acodec": "none", "vbr": 71.199, "downloader_options": {"http_chunk_size": 10485760}, "container": "webm_dash", "format": "278 - 192x144 (144p)", "protocol": "https", "http_headers": {"User-Agent": "Mozilla/5.0 (Windows NT 10.0; Win64; x64) AppleWebKit/537.36 (KHTML, like Gecko) Chrome/74.0.3729.92 Safari/537.36", "Accept-Charset": "ISO-8859-1,utf-8;q=0.7,*;q=0.7", "Accept": "text/html,application/xhtml+xml,application/xml;q=0.9,*/*;q=0.8", "Accept-Encoding": "gzip, deflate", "Accept-Language": "en-us,en;q=0.5"}}, {"asr": null, "filesize": 4052100, "format_id": "395", "format_note": "240p", "fps": 30, "height": 240, "quality": 1, "tbr": 102.191, "url": "https://rr5---sn-0opoxu-ihv6.googlevideo.com/videoplayback?expire=1670795486&ei=fvyVY9KCFsKXkway_LHwCQ&ip=189.173.225.87&id=o-ABmi8SIQqP8x1u2FH9kwFA74M54JlyN7Di6pYTfCz2sD&itag=395&aitags=133%2C134%2C135%2C160%2C242%2C243%2C244%2C278%2C394%2C395%2C396%2C397&source=youtube&requiressl=yes&mh=YF&mm=31%2C29&mn=sn-0opoxu-ihv6%2Csn-q4flrnlz&ms=au%2Crdu&mv=m&mvi=5&pl=24&initcwndbps=861250&vprv=1&mime=video%2Fmp4&ns=ajrLFqX9024sAm2XfGBg_0MJ&gir=yes&clen=4052100&dur=317.216&lmt=1627506652720072&mt=1670773517&fvip=2&keepalive=yes&fexp=24001373%2C24007246&c=WEB&txp=5532434&n=p7s-ahxPTjp8JeEob&sparams=expire%2Cei%2Cip%2Cid%2Caitags%2Csource%2Crequiressl%2Cvprv%2Cmime%2Cns%2Cgir%2Cclen%2Cdur%2Clmt&lsparams=mh%2Cmm%2Cmn%2Cms%2Cmv%2Cmvi%2Cpl%2Cinitcwndbps&lsig=AG3C_xAwRAIgC8rJ6vIt4Ro1Bt8K-TdvjH4J0GGyHlITJ9Zy9pTc1SYCIFhbzE6gbtj_1u39IzMDFYNrTe2syAnL7NTALA5RwuYH&sig=AOq0QJ8wRQIgL2qohLz78Yx4-cEAr1IhuaxvNsFoRulq1o4LjzeKKmYCIQCHgFWt93g9j86C9panFwAzA0EzggSQCHqgB5uJ8SheBw==", "width": 320, "ext": "mp4", "vcodec": "av01.0.00M.08.0.110.06.01.06.0", "acodec": "none", "vbr": 102.191, "downloader_options": {"http_chunk_size": 10485760}, "container": "mp4_dash", "format": "395 - 320x240 (240p)", "protocol": "https", "http_headers": {"User-Agent": "Mozilla/5.0 (Windows NT 10.0; Win64; x64) AppleWebKit/537.36 (KHTML, like Gecko) Chrome/74.0.3729.92 Safari/537.36", "Accept-Charset": "ISO-8859-1,utf-8;q=0.7,*;q=0.7", "Accept": "text/html,application/xhtml+xml,application/xml;q=0.9,*/*;q=0.8", "Accept-Encoding": "gzip, deflate", "Accept-Language": "en-us,en;q=0.5"}}, {"asr": null, "filesize": 4774088, "format_id": "133", "format_note": "240p", "fps": 30, "height": 240, "quality": 1, "tbr": 120.399, "url": "https://rr5---sn-0opoxu-ihv6.googlevideo.com/videoplayback?expire=1670795486&ei=fvyVY9KCFsKXkway_LHwCQ&ip=189.173.225.87&id=o-ABmi8SIQqP8x1u2FH9kwFA74M54JlyN7Di6pYTfCz2sD&itag=133&aitags=133%2C134%2C135%2C160%2C242%2C243%2C244%2C278%2C394%2C395%2C396%2C397&source=youtube&requiressl=yes&mh=YF&mm=31%2C29&mn=sn-0opoxu-ihv6%2Csn-q4flrnlz&ms=au%2Crdu&mv=m&mvi=5&pl=24&initcwndbps=861250&vprv=1&mime=video%2Fmp4&ns=ajrLFqX9024sAm2XfGBg_0MJ&gir=yes&clen=4774088&dur=317.216&lmt=1576357888872786&mt=1670773517&fvip=2&keepalive=yes&fexp=24001373%2C24007246&c=WEB&txp=5532432&n=p7s-ahxPTjp8JeEob&sparams=expire%2Cei%2Cip%2Cid%2Caitags%2Csource%2Crequiressl%2Cvprv%2Cmime%2Cns%2Cgir%2Cclen%2Cdur%2Clmt&lsparams=mh%2Cmm%2Cmn%2Cms%2Cmv%2Cmvi%2Cpl%2Cinitcwndbps&lsig=AG3C_xAwRQIgeXfAxZRfww8k1ecnQsRsZNBJhUmJLY7J0kWSMSLHAzQCIQDpLatMLxPSOGStQPIoZM4qKp9VX5ldDwNd4fi7b7d2qA%3D%3D&sig=AOq0QJ8wRQIgZwBTMmC9tUW3qMZbMVJa8QRhp-4K48aoCevtFCIBTdsCIQDiXMDIKgoEQIM2XlDLf8H0xdI2QY4UzBuV-8AhDZoPNQ==", "width": 320, "ext": "mp4", "vcodec": "avc1.4d400d", "acodec": "none", "vbr": 120.399, "downloader_options": {"http_chunk_size": 10485760}, "container": "mp4_dash", "format": "133 - 320x240 (240p)", "protocol": "https", "http_headers": {"User-Agent": "Mozilla/5.0 (Windows NT 10.0; Win64; x64) AppleWebKit/537.36 (KHTML, like Gecko) Chrome/74.0.3729.92 Safari/537.36", "Accept-Charset": "ISO-8859-1,utf-8;q=0.7,*;q=0.7", "Accept": "text/html,application/xhtml+xml,application/xml;q=0.9,*/*;q=0.8", "Accept-Encoding": "gzip, deflate", "Accept-Language": "en-us,en;q=0.5"}}, {"asr": null, "filesize": 5752869, "format_id": "242", "format_note": "240p", "fps": 30, "height": 240, "quality": 1, "tbr": 145.083, "url": "https://rr5---sn-0opoxu-ihv6.googlevideo.com/videoplayback?expire=1670795486&ei=fvyVY9KCFsKXkway_LHwCQ&ip=189.173.225.87&id=o-ABmi8SIQqP8x1u2FH9kwFA74M54JlyN7Di6pYTfCz2sD&itag=242&aitags=133%2C134%2C135%2C160%2C242%2C243%2C244%2C278%2C394%2C395%2C396%2C397&source=youtube&requiressl=yes&mh=YF&mm=31%2C29&mn=sn-0opoxu-ihv6%2Csn-q4flrnlz&ms=au%2Crdu&mv=m&mvi=5&pl=24&initcwndbps=861250&vprv=1&mime=video%2Fwebm&ns=ajrLFqX9024sAm2XfGBg_0MJ&gir=yes&clen=5752869&dur=317.216&lmt=1576358072847263&mt=1670773517&fvip=2&keepalive=yes&fexp=24001373%2C24007246&c=WEB&txp=5531432&n=p7s-ahxPTjp8JeEob&sparams=expire%2Cei%2Cip%2Cid%2Caitags%2Csource%2Crequiressl%2Cvprv%2Cmime%2Cns%2Cgir%2Cclen%2Cdur%2Clmt&lsparams=mh%2Cmm%2Cmn%2Cms%2Cmv%2Cmvi%2Cpl%2Cinitcwndbps&lsig=AG3C_xAwRAIgISpUR7OZDNC3sKFkbOQ1l_5D3RyXPTrMKTyeEy2OOXECICIFascyRd67JI1iwz1HyLIbXIDsHS53Yfs0yPSzO3Ay&sig=AOq0QJ8wRgIhAIgQIuPq7wDAUhjoVsBMM9vcJiB14d13cBYIkEZDLwxyAiEAjjXRFpGxhVW92-o3_S9hCQzICQoz75_4_UErlSW8PQM=", "width": 320, "ext": "webm", "vcodec": "vp9", "acodec": "none", "vbr": 145.083, "downloader_options": {"http_chunk_size": 10485760}, "container": "webm_dash", "format": "242 - 320x240 (240p)", "protocol": "https", "http_headers": {"User-Agent": "Mozilla/5.0 (Windows NT 10.0; Win64; x64) AppleWebKit/537.36 (KHTML, like Gecko) Chrome/74.0.3729.92 Safari/537.36", "Accept-Charset": "ISO-8859-1,utf-8;q=0.7,*;q=0.7", "Accept": "text/html,application/xhtml+xml,application/xml;q=0.9,*/*;q=0.8", "Accept-Encoding": "gzip, deflate", "Accept-Language": "en-us,en;q=0.5"}}, {"asr": null, "filesize": 7746377, "format_id": "396", "format_note": "360p", "fps": 30, "height": 360, "quality": 2, "tbr": 195.359, "url": "https://rr5---sn-0opoxu-ihv6.googlevideo.com/videoplayback?expire=1670795486&ei=fvyVY9KCFsKXkway_LHwCQ&ip=189.173.225.87&id=o-ABmi8SIQqP8x1u2FH9kwFA74M54JlyN7Di6pYTfCz2sD&itag=396&aitags=133%2C134%2C135%2C160%2C242%2C243%2C244%2C278%2C394%2C395%2C396%2C397&source=youtube&requiressl=yes&mh=YF&mm=31%2C29&mn=sn-0opoxu-ihv6%2Csn-q4flrnlz&ms=au%2Crdu&mv=m&mvi=5&pl=24&initcwndbps=861250&vprv=1&mime=video%2Fmp4&ns=ajrLFqX9024sAm2XfGBg_0MJ&gir=yes&clen=7746377&dur=317.216&lmt=1627508527239131&mt=1670773517&fvip=2&keepalive=yes&fexp=24001373%2C24007246&c=WEB&txp=5532434&n=p7s-ahxPTjp8JeEob&sparams=expire%2Cei%2Cip%2Cid%2Caitags%2Csource%2Crequiressl%2Cvprv%2Cmime%2Cns%2Cgir%2Cclen%2Cdur%2Clmt&lsparams=mh%2Cmm%2Cmn%2Cms%2Cmv%2Cmvi%2Cpl%2Cinitcwndbps&lsig=AG3C_xAwRgIhAK-KMi889AnlBnyP-n4-RejVgrAkpxB0ouFADth4oB2fAiEAynonuE7xBCnow2SzG5HLGNHHzSr2t1wijJqfs1Py12o%3D&sig=AOq0QJ8wRQIhAPYIfuOt29mVzVJA4tz8q-VpEHhURvvY-ymBbKsPbBq9AiBtzSIf8YEo7rAK7XnTwIXr-W-E-4hI1L_iqKmDxfXMKQ==", "width": 480, "ext": "mp4", "vcodec": "av01.0.01M.08.0.110.06.01.06.0", "acodec": "none", "vbr": 195.359, "downloader_options": {"http_chunk_size": 10485760}, "container": "mp4_dash", "format": "396 - 480x360 (360p)", "protocol": "https", "http_headers": {"User-Agent": "Mozilla/5.0 (Windows NT 10.0; Win64; x64) AppleWebKit/537.36 (KHTML, like Gecko) Chrome/74.0.3729.92 Safari/537.36", "Accept-Charset": "ISO-8859-1,utf-8;q=0.7,*;q=0.7", "Accept": "text/html,application/xhtml+xml,application/xml;q=0.9,*/*;q=0.8", "Accept-Encoding": "gzip, deflate", "Accept-Language": "en-us,en;q=0.5"}}, {"asr": null, "filesize": 9906020, "format_id": "243", "format_note": "360p", "fps": 30, "height": 360, "quality": 2, "tbr": 249.823, "url": "https://rr5---sn-0opoxu-ihv6.googlevideo.com/videoplayback?expire=1670795486&ei=fvyVY9KCFsKXkway_LHwCQ&ip=189.173.225.87&id=o-ABmi8SIQqP8x1u2FH9kwFA74M54JlyN7Di6pYTfCz2sD&itag=243&aitags=133%2C134%2C135%2C160%2C242%2C243%2C244%2C278%2C394%2C395%2C396%2C397&source=youtube&requiressl=yes&mh=YF&mm=31%2C29&mn=sn-0opoxu-ihv6%2Csn-q4flrnlz&ms=au%2Crdu&mv=m&mvi=5&pl=24&initcwndbps=861250&vprv=1&mime=video%2Fwebm&ns=ajrLFqX9024sAm2XfGBg_0MJ&gir=yes&clen=9906020&dur=317.216&lmt=1576358072845702&mt=1670773517&fvip=2&keepalive=yes&fexp=24001373%2C24007246&c=WEB&txp=5531432&n=p7s-ahxPTjp8JeEob&sparams=expire%2Cei%2Cip%2Cid%2Caitags%2Csource%2Crequiressl%2Cvprv%2Cmime%2Cns%2Cgir%2Cclen%2Cdur%2Clmt&lsparams=mh%2Cmm%2Cmn%2Cms%2Cmv%2Cmvi%2Cpl%2Cinitcwndbps&lsig=AG3C_xAwRAIgCLuWWSfiAwZaa_FMAiumhSLov05tLCqf83Ks1zCEfrcCIG2PQfFaBBrGabPyypWihVZ5Zv5HhW12NfJZmHU-we80&sig=AOq0QJ8wRgIhAKUELrHUhynzBlpHDhSY0gL2ltG2L549xI04xOr-YQagAiEAtY57MSBqcNQntiRCPYQcXR6v02LNx8t7OVOCqa66kts=", "width": 480, "ext": "webm", "vcodec": "vp9", "acodec": "none", "vbr": 249.823, "downloader_options": {"http_chunk_size": 10485760}, "container": "webm_dash", "format": "243 - 480x360 (360p)", "protocol": "https", "http_headers": {"User-Agent": "Mozilla/5.0 (Windows NT 10.0; Win64; x64) AppleWebKit/537.36 (KHTML, like Gecko) Chrome/74.0.3729.92 Safari/537.36", "Accept-Charset": "ISO-8859-1,utf-8;q=0.7,*;q=0.7", "Accept": "text/html,application/xhtml+xml,application/xml;q=0.9,*/*;q=0.8", "Accept-Encoding": "gzip, deflate", "Accept-Language": "en-us,en;q=0.5"}}, {"asr": null, "filesize": 11441761, "format_id": "134", "format_note": "360p", "fps": 30, "height": 360, "quality": 2, "tbr": 288.554, "url": "https://rr5---sn-0opoxu-ihv6.googlevideo.com/videoplayback?expire=1670795486&ei=fvyVY9KCFsKXkway_LHwCQ&ip=189.173.225.87&id=o-ABmi8SIQqP8x1u2FH9kwFA74M54JlyN7Di6pYTfCz2sD&itag=134&aitags=133%2C134%2C135%2C160%2C242%2C243%2C244%2C278%2C394%2C395%2C396%2C397&source=youtube&requiressl=yes&mh=YF&mm=31%2C29&mn=sn-0opoxu-ihv6%2Csn-q4flrnlz&ms=au%2Crdu&mv=m&mvi=5&pl=24&initcwndbps=861250&vprv=1&mime=video%2Fmp4&ns=ajrLFqX9024sAm2XfGBg_0MJ&gir=yes&clen=11441761&dur=317.216&lmt=1576357888874977&mt=1670773517&fvip=2&keepalive=yes&fexp=24001373%2C24007246&c=WEB&txp=5532432&n=p7s-ahxPTjp8JeEob&sparams=expire%2Cei%2Cip%2Cid%2Caitags%2Csource%2Crequiressl%2Cvprv%2Cmime%2Cns%2Cgir%2Cclen%2Cdur%2Clmt&lsparams=mh%2Cmm%2Cmn%2Cms%2Cmv%2Cmvi%2Cpl%2Cinitcwndbps&lsig=AG3C_xAwRQIgcC-5Z1t5AC3338o-8mR4-jjPqU9lxW2h2UcJq_WxKHECIQDDUK5jnMa3QtKnj0DzVNbUHUQ_ljv0aJ2JyDZWZAtueg%3D%3D&sig=AOq0QJ8wRQIgDA6c59yAfjbVXrJ9KN9lEKoc83iOn42KUCHykyn10qACIQDXOpmB7KVBgzD7oYhA6ZE5bd4Um6R-U-A1umJ_D-VU0Q==", "width": 480, "ext": "mp4", "vcodec": "avc1.4d401e", "acodec": "none", "vbr": 288.554, "downloader_options": {"http_chunk_size": 10485760}, "container": "mp4_dash", "format": "134 - 480x360 (360p)", "protocol": "https", "http_headers": {"User-Agent": "Mozilla/5.0 (Windows NT 10.0; Win64; x64) AppleWebKit/537.36 (KHTML, like Gecko) Chrome/74.0.3729.92 Safari/537.36", "Accept-Charset": "ISO-8859-1,utf-8;q=0.7,*;q=0.7", "Accept": "text/html,application/xhtml+xml,application/xml;q=0.9,*/*;q=0.8", "Accept-Encoding": "gzip, deflate", "Accept-Language": "en-us,en;q=0.5"}}, {"asr": null, "filesize": 13361259, "format_id": "397", "format_note": "480p", "fps": 30, "height": 480, "quality": 3, "tbr": 336.963, "url": "https://rr5---sn-0opoxu-ihv6.googlevideo.com/videoplayback?expire=1670795486&ei=fvyVY9KCFsKXkway_LHwCQ&ip=189.173.225.87&id=o-ABmi8SIQqP8x1u2FH9kwFA74M54JlyN7Di6pYTfCz2sD&itag=397&aitags=133%2C134%2C135%2C160%2C242%2C243%2C244%2C278%2C394%2C395%2C396%2C397&source=youtube&requiressl=yes&mh=YF&mm=31%2C29&mn=sn-0opoxu-ihv6%2Csn-q4flrnlz&ms=au%2Crdu&mv=m&mvi=5&pl=24&initcwndbps=861250&vprv=1&mime=video%2Fmp4&ns=ajrLFqX9024sAm2XfGBg_0MJ&gir=yes&clen=13361259&dur=317.216&lmt=1627507378318111&mt=1670773517&fvip=2&keepalive=yes&fexp=24001373%2C24007246&c=WEB&txp=5532434&n=p7s-ahxPTjp8JeEob&sparams=expire%2Cei%2Cip%2Cid%2Caitags%2Csource%2Crequiressl%2Cvprv%2Cmime%2Cns%2Cgir%2Cclen%2Cdur%2Clmt&lsparams=mh%2Cmm%2Cmn%2Cms%2Cmv%2Cmvi%2Cpl%2Cinitcwndbps&lsig=AG3C_xAwRgIhAPIZvnnOQES_hrRta9PBY-eZCqgWBJOsyQbrjB0ZbZ4IAiEAt0GfhESJssvNG79866SAKfVj_gZ2UztB9ZkNaFvDqOc%3D&sig=AOq0QJ8wRQIgW6sy-wigVGQHit071KlBddHTWaSJWTHi19Rh9Fr2Ek8CIQCRKeMc5PtxekuAmAXwyYwJbC-SBzwlvd5wWotrWDfw_A==", "width": 640, "ext": "mp4", "vcodec": "av01.0.04M.08.0.110.06.01.06.0", "acodec": "none", "vbr": 336.963, "downloader_options": {"http_chunk_size": 10485760}, "container": "mp4_dash", "format": "397 - 640x480 (480p)", "protocol": "https", "http_headers": {"User-Agent": "Mozilla/5.0 (Windows NT 10.0; Win64; x64) AppleWebKit/537.36 (KHTML, like Gecko) Chrome/74.0.3729.92 Safari/537.36", "Accept-Charset": "ISO-8859-1,utf-8;q=0.7,*;q=0.7", "Accept": "text/html,application/xhtml+xml,application/xml;q=0.9,*/*;q=0.8", "Accept-Encoding": "gzip, deflate", "Accept-Language": "en-us,en;q=0.5"}}, {"asr": null, "filesize": 16387563, "format_id": "244", "format_note": "480p", "fps": 30, "height": 480, "quality": 3, "tbr": 413.284, "url": "https://rr5---sn-0opoxu-ihv6.googlevideo.com/videoplayback?expire=1670795486&ei=fvyVY9KCFsKXkway_LHwCQ&ip=189.173.225.87&id=o-ABmi8SIQqP8x1u2FH9kwFA74M54JlyN7Di6pYTfCz2sD&itag=244&aitags=133%2C134%2C135%2C160%2C242%2C243%2C244%2C278%2C394%2C395%2C396%2C397&source=youtube&requiressl=yes&mh=YF&mm=31%2C29&mn=sn-0opoxu-ihv6%2Csn-q4flrnlz&ms=au%2Crdu&mv=m&mvi=5&pl=24&initcwndbps=861250&vprv=1&mime=video%2Fwebm&ns=ajrLFqX9024sAm2XfGBg_0MJ&gir=yes&clen=16387563&dur=317.216&lmt=1576358072841907&mt=1670773517&fvip=2&keepalive=yes&fexp=24001373%2C24007246&c=WEB&txp=5531432&n=p7s-ahxPTjp8JeEob&sparams=expire%2Cei%2Cip%2Cid%2Caitags%2Csource%2Crequiressl%2Cvprv%2Cmime%2Cns%2Cgir%2Cclen%2Cdur%2Clmt&lsparams=mh%2Cmm%2Cmn%2Cms%2Cmv%2Cmvi%2Cpl%2Cinitcwndbps&lsig=AG3C_xAwRQIhAP6uuvROvtbaEHC6uzcmAQ5ltPQVs6vCBRcRnbTZpMDtAiAyLGa71ySa1q9NrQjFKgyCmPIokTAyVOWBApcImw1mGA%3D%3D&sig=AOq0QJ8wRQIhAME8fCLW23jkT9d6b8R_QFaP2yQT2aApU3jtARMkEK-2AiBc8mVhVigMs4GgYnvvm0WVY1v-1XhCOj4liX4d0n0Vbw==", "width": 640, "ext": "webm", "vcodec": "vp9", "acodec": "none", "vbr": 413.284, "downloader_options": {"http_chunk_size": 10485760}, "container": "webm_dash", "format": "244 - 640x480 (480p)", "protocol": "https", "http_headers": {"User-Agent": "Mozilla/5.0 (Windows NT 10.0; Win64; x64) AppleWebKit/537.36 (KHTML, like Gecko) Chrome/74.0.3729.92 Safari/537.36", "Accept-Charset": "ISO-8859-1,utf-8;q=0.7,*;q=0.7", "Accept": "text/html,application/xhtml+xml,application/xml;q=0.9,*/*;q=0.8", "Accept-Encoding": "gzip, deflate", "Accept-Language": "en-us,en;q=0.5"}}, {"asr": null, "filesize": 21904266, "format_id": "135", "format_note": "480p", "fps": 30, "height": 480, "quality": 3, "tbr": 552.412, "url": "https://rr5---sn-0opoxu-ihv6.googlevideo.com/videoplayback?expire=1670795486&ei=fvyVY9KCFsKXkway_LHwCQ&ip=189.173.225.87&id=o-ABmi8SIQqP8x1u2FH9kwFA74M54JlyN7Di6pYTfCz2sD&itag=135&aitags=133%2C134%2C135%2C160%2C242%2C243%2C244%2C278%2C394%2C395%2C396%2C397&source=youtube&requiressl=yes&mh=YF&mm=31%2C29&mn=sn-0opoxu-ihv6%2Csn-q4flrnlz&ms=au%2Crdu&mv=m&mvi=5&pl=24&initcwndbps=861250&vprv=1&mime=video%2Fmp4&ns=ajrLFqX9024sAm2XfGBg_0MJ&gir=yes&clen=21904266&dur=317.216&lmt=1576357888921596&mt=1670773517&fvip=2&keepalive=yes&fexp=24001373%2C24007246&c=WEB&txp=5532432&n=p7s-ahxPTjp8JeEob&sparams=expire%2Cei%2Cip%2Cid%2Caitags%2Csource%2Crequiressl%2Cvprv%2Cmime%2Cns%2Cgir%2Cclen%2Cdur%2Clmt&lsparams=mh%2Cmm%2Cmn%2Cms%2Cmv%2Cmvi%2Cpl%2Cinitcwndbps&lsig=AG3C_xAwRQIgXth5SBrhDz5n_tiDtpwAVCgbbX3RNlg1JT9nlsm84MgCIQDVf44Fn-1ObqFnPDis6bAVyk22x5huVRqFdA9QgLhMJw%3D%3D&sig=AOq0QJ8wRgIhAKOsxoAbhd_0VjP1TiWY56aCYMVTn5lDfn1spa-oYMJ6AiEA7hhW8QBCG20RxKvyGoSCeTY54u1oJfn4j5PBxCN08-Y=", "width": 640, "ext": "mp4", "vcodec": "avc1.4d401e", "acodec": "none", "vbr": 552.412, "downloader_options": {"http_chunk_size": 10485760}, "container": "mp4_dash", "format": "135 - 640x480 (480p)", "protocol": "https", "http_headers": {"User-Agent": "Mozilla/5.0 (Windows NT 10.0; Win64; x64) AppleWebKit/537.36 (KHTML, like Gecko) Chrome/74.0.3729.92 Safari/537.36", "Accept-Charset": "ISO-8859-1,utf-8;q=0.7,*;q=0.7", "Accept": "text/html,application/xhtml+xml,application/xml;q=0.9,*/*;q=0.8", "Accept-Encoding": "gzip, deflate", "Accept-Language": "en-us,en;q=0.5"}}, {"asr": 44100, "filesize": null, "format_id": "18", "format_note": "360p", "fps": 30, "height": 360, "quality": 2, "tbr": 417.611, "url": "https://rr5---sn-0opoxu-ihv6.googlevideo.com/videoplayback?expire=1670795486&ei=fvyVY9KCFsKXkway_LHwCQ&ip=189.173.225.87&id=o-ABmi8SIQqP8x1u2FH9kwFA74M54JlyN7Di6pYTfCz2sD&itag=18&source=youtube&requiressl=yes&mh=YF&mm=31%2C29&mn=sn-0opoxu-ihv6%2Csn-q4flrnlz&ms=au%2Crdu&mv=m&mvi=5&pl=24&initcwndbps=861250&vprv=1&mime=video%2Fmp4&ns=-6okoeQnFx2ykP4r2_FI8bcJ&cnr=14&ratebypass=yes&dur=317.277&lmt=1665147231346096&mt=1670773517&fvip=2&fexp=24001373%2C24007246&c=WEB&txp=5538434&n=jvvLOm9NaqGXHeKYg&sparams=expire%2Cei%2Cip%2Cid%2Citag%2Csource%2Crequiressl%2Cvprv%2Cmime%2Cns%2Ccnr%2Cratebypass%2Cdur%2Clmt&lsparams=mh%2Cmm%2Cmn%2Cms%2Cmv%2Cmvi%2Cpl%2Cinitcwndbps&lsig=AG3C_xAwRQIgL8pinscdT4OZBbrFONk_lIm1nwWA3DYfFdWaluAM278CIQDiORDBXBsWtj-QomkjPCsXNeSO4PhWV0P1NHTpmW0d3g%3D%3D&sig=AOq0QJ8wRAIgTyDcVuRX8C-kECesqNlT7eO1AZtk1znMncgbr1mReFkCIBEj_gni46zpbnHSDqtgkzVLAfYvQxKhPrOV8SmcAPQE", "width": 480, "ext": "mp4", "vcodec": "avc1.42001E", "acodec": "mp4a.40.2", "format": "18 - 480x360 (360p)", "protocol": "https", "http_headers": {"User-Agent": "Mozilla/5.0 (Windows NT 10.0; Win64; x64) AppleWebKit/537.36 (KHTML, like Gecko) Chrome/74.0.3729.92 Safari/537.36", "Accept-Charset": "ISO-8859-1,utf-8;q=0.7,*;q=0.7", "Accept": "text/html,application/xhtml+xml,application/xml;q=0.9,*/*;q=0.8", "Accept-Encoding": "gzip, deflate", "Accept-Language": "en-us,en;q=0.5"}}], "thumbnails": [{"height": 94, "url": "https://i.ytimg.com/vi/MlzTET_8SQg/hqdefault.jpg?sqp=-oaymwEbCKgBEF5IVfKriqkDDggBFQAAiEIYAXABwAEG&rs=AOn4CLCsVn2zGWkt9-uVKn-vcu0sM8AZ0w", "width": 168, "resolution": "168x94", "id": "0"}, {"height": 110, "url": "https://i.ytimg.com/vi/MlzTET_8SQg/hqdefault.jpg?sqp=-oaymwEbCMQBEG5IVfKriqkDDggBFQAAiEIYAXABwAEG&rs=AOn4CLDO7hMDGbV1d-cBfzCNPV-_ARC_Zw", "width": 196, "resolution": "196x110", "id": "1"}, {"height": 138, "url": "https://i.ytimg.com/vi/MlzTET_8SQg/hqdefault.jpg?sqp=-oaymwEcCPYBEIoBSFXyq4qpAw4IARUAAIhCGAFwAcABBg==&rs=AOn4CLCtucT_dfnlAi0e0f4m_Qa6w6m6TA", "width": 246, "resolution": "246x138", "id": "2"}, {"height": 188, "url": "https://i.ytimg.com/vi/MlzTET_8SQg/hqdefault.jpg?sqp=-oaymwEcCNACELwBSFXyq4qpAw4IARUAAIhCGAFwAcABBg==&rs=AOn4CLCkAYJH-O2x6IkpUcEwG0qFLYhpog", "width": 336, "resolution": "336x188", "id": "3"}, {"height": 1080, "url": "https://i.ytimg.com/vi_webp/MlzTET_8SQg/maxresdefault.webp", "width": 1920, "resolution": "1920x1080", "id": "4"}], "description": "Official music video for \u2018Overkill\u2019 by Mot\u00f6rhead \nListen to Overkill : https://motorhead.lnk.to/overkillID \n\nSubscribe to the official Mot\u00f6rhead YouTube Channel: https://motorhead.lnk.to/subscribeYD \n\nFollow Mot\u00f6rhead: \nFacebook: https://motorhead.lnk.to/followFI \nTwitter: https://motorhead.lnk.to/followTI \nInstagram: https://motorhead.lnk.to/followII \nWebsite: https://motorhead.lnk.to/followWI \nSpotify: https://motorhead.lnk.to/followSI \nYouTube: https://motorhead.lnk.to/subscribeYD\n\nOverkill appears on Mot\u00f6rhead\u2019s album \u2018Overkill\u2019. Originally released on Bronze Records on 24th March 1979, produced by Jimmy Miller. The line up on this album was Lemmy, Fast Eddie Clarke and Philthy Animal Taylor. \nOnly way to feel the noise is when it's good and loud\nSo good I can't believe it, screaming with the crowd\nDon't sweat it, we'll get it back to you\nDon't sweat it, we'll get it back to you\nOverkill, overkill, overkill\nOn your feet you feel the beat, it goes straight to your spine\nShake your head you must be dead if it don't make you fly\nDon't sweat it, we'll get it back to you\nDon't sweat it, we'll get it back to you\nOverkill, overkill, overkill\nKnow your body's made to move, ya feel it in your guts\nRock 'n' roll ain't worth the name if it don't make ya strut\nDon't sweat it, we'll get it back to you\nDon't sweat it, we'll get it back to you\nOverkill, overkill, overkill\n\n#lemmy #fasteddie #philthyanimal #overkill #aceofspades #nwobhm #jimmymiller #bronzerecords #borntolose #livetowin", "upload_date": "20190701", "uploader": "Mot\u00f6rhead Official", "uploader_id": "UCbPCDmtTU-W4SdA8abZtWpA", "uploader_url": "http://www.youtube.com/channel/UCbPCDmtTU-W4SdA8abZtWpA", "channel_id": "UCbPCDmtTU-W4SdA8abZtWpA", "channel_url": "https://www.youtube.com/channel/UCbPCDmtTU-W4SdA8abZtWpA", "duration": 317, "view_count": 14938752, "average_rating": null, "age_limit": 0, "webpage_url": "https://www.youtube.com/watch?v=MlzTET_8SQg", "categories": ["Music"], "tags": ["Motorhead", "Overkill"], "is_live": null, "subtitles": {"en-US": [{"ext": "srv1", "url": "https://www.youtube.com/api/timedtext?v=MlzTET_8SQg&xoaf=5&hl=en&ip=0.0.0.0&ipbits=0&expire=1670799086&sparams=ip%2Cipbits%2Cexpire%2Cv%2Cxoaf&signature=D307EA92387D1AFAA7114DA71C3D260E4B4746BE.768A476FAE903C7BA0FA22A7490DEA99991DE422&key=yt8&lang=en-US&fmt=srv1"}, {"ext": "srv2", "url": "https://www.youtube.com/api/timedtext?v=MlzTET_8SQg&xoaf=5&hl=en&ip=0.0.0.0&ipbits=0&expire=1670799086&sparams=ip%2Cipbits%2Cexpire%2Cv%2Cxoaf&signature=D307EA92387D1AFAA7114DA71C3D260E4B4746BE.768A476FAE903C7BA0FA22A7490DEA99991DE422&key=yt8&lang=en-US&fmt=srv2"}, {"ext": "srv3", "url": "https://www.youtube.com/api/timedtext?v=MlzTET_8SQg&xoaf=5&hl=en&ip=0.0.0.0&ipbits=0&expire=1670799086&sparams=ip%2Cipbits%2Cexpire%2Cv%2Cxoaf&signature=D307EA92387D1AFAA7114DA71C3D260E4B4746BE.768A476FAE903C7BA0FA22A7490DEA99991DE422&key=yt8&lang=en-US&fmt=srv3"}, {"ext": "ttml", "url": "https://www.youtube.com/api/timedtext?v=MlzTET_8SQg&xoaf=5&hl=en&ip=0.0.0.0&ipbits=0&expire=1670799086&sparams=ip%2Cipbits%2Cexpire%2Cv%2Cxoaf&signature=D307EA92387D1AFAA7114DA71C3D260E4B4746BE.768A476FAE903C7BA0FA22A7490DEA99991DE422&key=yt8&lang=en-US&fmt=ttml"}, {"ext": "vtt", "url": "https://www.youtube.com/api/timedtext?v=MlzTET_8SQg&xoaf=5&hl=en&ip=0.0.0.0&ipbits=0&expire=1670799086&sparams=ip%2Cipbits%2Cexpire%2Cv%2Cxoaf&signature=D307EA92387D1AFAA7114DA71C3D260E4B4746BE.768A476FAE903C7BA0FA22A7490DEA99991DE422&key=yt8&lang=en-US&fmt=vtt"}], "fr": [{"ext": "srv1", "url": "https://www.youtube.com/api/timedtext?v=MlzTET_8SQg&xoaf=5&hl=en&ip=0.0.0.0&ipbits=0&expire=1670799086&sparams=ip%2Cipbits%2Cexpire%2Cv%2Cxoaf&signature=D307EA92387D1AFAA7114DA71C3D260E4B4746BE.768A476FAE903C7BA0FA22A7490DEA99991DE422&key=yt8&lang=fr&fmt=srv1"}, {"ext": "srv2", "url": "https://www.youtube.com/api/timedtext?v=MlzTET_8SQg&xoaf=5&hl=en&ip=0.0.0.0&ipbits=0&expire=1670799086&sparams=ip%2Cipbits%2Cexpire%2Cv%2Cxoaf&signature=D307EA92387D1AFAA7114DA71C3D260E4B4746BE.768A476FAE903C7BA0FA22A7490DEA99991DE422&key=yt8&lang=fr&fmt=srv2"}, {"ext": "srv3", "url": "https://www.youtube.com/api/timedtext?v=MlzTET_8SQg&xoaf=5&hl=en&ip=0.0.0.0&ipbits=0&expire=1670799086&sparams=ip%2Cipbits%2Cexpire%2Cv%2Cxoaf&signature=D307EA92387D1AFAA7114DA71C3D260E4B4746BE.768A476FAE903C7BA0FA22A7490DEA99991DE422&key=yt8&lang=fr&fmt=srv3"}, {"ext": "ttml", "url": "https://www.youtube.com/api/timedtext?v=MlzTET_8SQg&xoaf=5&hl=en&ip=0.0.0.0&ipbits=0&expire=1670799086&sparams=ip%2Cipbits%2Cexpire%2Cv%2Cxoaf&signature=D307EA92387D1AFAA7114DA71C3D260E4B4746BE.768A476FAE903C7BA0FA22A7490DEA99991DE422&key=yt8&lang=fr&fmt=ttml"}, {"ext": "vtt", "url": "https://www.youtube.com/api/timedtext?v=MlzTET_8SQg&xoaf=5&hl=en&ip=0.0.0.0&ipbits=0&expire=1670799086&sparams=ip%2Cipbits%2Cexpire%2Cv%2Cxoaf&signature=D307EA92387D1AFAA7114DA71C3D260E4B4746BE.768A476FAE903C7BA0FA22A7490DEA99991DE422&key=yt8&lang=fr&fmt=vtt"}], "de": [{"ext": "srv1", "url": "https://www.youtube.com/api/timedtext?v=MlzTET_8SQg&xoaf=5&hl=en&ip=0.0.0.0&ipbits=0&expire=1670799086&sparams=ip%2Cipbits%2Cexpire%2Cv%2Cxoaf&signature=D307EA92387D1AFAA7114DA71C3D260E4B4746BE.768A476FAE903C7BA0FA22A7490DEA99991DE422&key=yt8&lang=de&fmt=srv1"}, {"ext": "srv2", "url": "https://www.youtube.com/api/timedtext?v=MlzTET_8SQg&xoaf=5&hl=en&ip=0.0.0.0&ipbits=0&expire=1670799086&sparams=ip%2Cipbits%2Cexpire%2Cv%2Cxoaf&signature=D307EA92387D1AFAA7114DA71C3D260E4B4746BE.768A476FAE903C7BA0FA22A7490DEA99991DE422&key=yt8&lang=de&fmt=srv2"}, {"ext": "srv3", "url": "https://www.youtube.com/api/timedtext?v=MlzTET_8SQg&xoaf=5&hl=en&ip=0.0.0.0&ipbits=0&expire=1670799086&sparams=ip%2Cipbits%2Cexpire%2Cv%2Cxoaf&signature=D307EA92387D1AFAA7114DA71C3D260E4B4746BE.768A476FAE903C7BA0FA22A7490DEA99991DE422&key=yt8&lang=de&fmt=srv3"}, {"ext": "ttml", "url": "https://www.youtube.com/api/timedtext?v=MlzTET_8SQg&xoaf=5&hl=en&ip=0.0.0.0&ipbits=0&expire=1670799086&sparams=ip%2Cipbits%2Cexpire%2Cv%2Cxoaf&signature=D307EA92387D1AFAA7114DA71C3D260E4B4746BE.768A476FAE903C7BA0FA22A7490DEA99991DE422&key=yt8&lang=de&fmt=ttml"}, {"ext": "vtt", "url": "https://www.youtube.com/api/timedtext?v=MlzTET_8SQg&xoaf=5&hl=en&ip=0.0.0.0&ipbits=0&expire=1670799086&sparams=ip%2Cipbits%2Cexpire%2Cv%2Cxoaf&signature=D307EA92387D1AFAA7114DA71C3D260E4B4746BE.768A476FAE903C7BA0FA22A7490DEA99991DE422&key=yt8&lang=de&fmt=vtt"}], "it": [{"ext": "srv1", "url": "https://www.youtube.com/api/timedtext?v=MlzTET_8SQg&xoaf=5&hl=en&ip=0.0.0.0&ipbits=0&expire=1670799086&sparams=ip%2Cipbits%2Cexpire%2Cv%2Cxoaf&signature=D307EA92387D1AFAA7114DA71C3D260E4B4746BE.768A476FAE903C7BA0FA22A7490DEA99991DE422&key=yt8&lang=it&fmt=srv1"}, {"ext": "srv2", "url": "https://www.youtube.com/api/timedtext?v=MlzTET_8SQg&xoaf=5&hl=en&ip=0.0.0.0&ipbits=0&expire=1670799086&sparams=ip%2Cipbits%2Cexpire%2Cv%2Cxoaf&signature=D307EA92387D1AFAA7114DA71C3D260E4B4746BE.768A476FAE903C7BA0FA22A7490DEA99991DE422&key=yt8&lang=it&fmt=srv2"}, {"ext": "srv3", "url": "https://www.youtube.com/api/timedtext?v=MlzTET_8SQg&xoaf=5&hl=en&ip=0.0.0.0&ipbits=0&expire=1670799086&sparams=ip%2Cipbits%2Cexpire%2Cv%2Cxoaf&signature=D307EA92387D1AFAA7114DA71C3D260E4B4746BE.768A476FAE903C7BA0FA22A7490DEA99991DE422&key=yt8&lang=it&fmt=srv3"}, {"ext": "ttml", "url": "https://www.youtube.com/api/timedtext?v=MlzTET_8SQg&xoaf=5&hl=en&ip=0.0.0.0&ipbits=0&expire=1670799086&sparams=ip%2Cipbits%2Cexpire%2Cv%2Cxoaf&signature=D307EA92387D1AFAA7114DA71C3D260E4B4746BE.768A476FAE903C7BA0FA22A7490DEA99991DE422&key=yt8&lang=it&fmt=ttml"}, {"ext": "vtt", "url": "https://www.youtube.com/api/timedtext?v=MlzTET_8SQg&xoaf=5&hl=en&ip=0.0.0.0&ipbits=0&expire=1670799086&sparams=ip%2Cipbits%2Cexpire%2Cv%2Cxoaf&signature=D307EA92387D1AFAA7114DA71C3D260E4B4746BE.768A476FAE903C7BA0FA22A7490DEA99991DE422&key=yt8&lang=it&fmt=vtt"}], "pt": [{"ext": "srv1", "url": "https://www.youtube.com/api/timedtext?v=MlzTET_8SQg&xoaf=5&hl=en&ip=0.0.0.0&ipbits=0&expire=1670799086&sparams=ip%2Cipbits%2Cexpire%2Cv%2Cxoaf&signature=D307EA92387D1AFAA7114DA71C3D260E4B4746BE.768A476FAE903C7BA0FA22A7490DEA99991DE422&key=yt8&lang=pt&fmt=srv1"}, {"ext": "srv2", "url": "https://www.youtube.com/api/timedtext?v=MlzTET_8SQg&xoaf=5&hl=en&ip=0.0.0.0&ipbits=0&expire=1670799086&sparams=ip%2Cipbits%2Cexpire%2Cv%2Cxoaf&signature=D307EA92387D1AFAA7114DA71C3D260E4B4746BE.768A476FAE903C7BA0FA22A7490DEA99991DE422&key=yt8&lang=pt&fmt=srv2"}, {"ext": "srv3", "url": "https://www.youtube.com/api/timedtext?v=MlzTET_8SQg&xoaf=5&hl=en&ip=0.0.0.0&ipbits=0&expire=1670799086&sparams=ip%2Cipbits%2Cexpire%2Cv%2Cxoaf&signature=D307EA92387D1AFAA7114DA71C3D260E4B4746BE.768A476FAE903C7BA0FA22A7490DEA99991DE422&key=yt8&lang=pt&fmt=srv3"}, {"ext": "ttml", "url": "https://www.youtube.com/api/timedtext?v=MlzTET_8SQg&xoaf=5&hl=en&ip=0.0.0.0&ipbits=0&expire=1670799086&sparams=ip%2Cipbits%2Cexpire%2Cv%2Cxoaf&signature=D307EA92387D1AFAA7114DA71C3D260E4B4746BE.768A476FAE903C7BA0FA22A7490DEA99991DE422&key=yt8&lang=pt&fmt=ttml"}, {"ext": "vtt", "url": "https://www.youtube.com/api/timedtext?v=MlzTET_8SQg&xoaf=5&hl=en&ip=0.0.0.0&ipbits=0&expire=1670799086&sparams=ip%2Cipbits%2Cexpire%2Cv%2Cxoaf&signature=D307EA92387D1AFAA7114DA71C3D260E4B4746BE.768A476FAE903C7BA0FA22A7490DEA99991DE422&key=yt8&lang=pt&fmt=vtt"}], "es": [{"ext": "srv1", "url": "https://www.youtube.com/api/timedtext?v=MlzTET_8SQg&xoaf=5&hl=en&ip=0.0.0.0&ipbits=0&expire=1670799086&sparams=ip%2Cipbits%2Cexpire%2Cv%2Cxoaf&signature=D307EA92387D1AFAA7114DA71C3D260E4B4746BE.768A476FAE903C7BA0FA22A7490DEA99991DE422&key=yt8&lang=es&fmt=srv1"}, {"ext": "srv2", "url": "https://www.youtube.com/api/timedtext?v=MlzTET_8SQg&xoaf=5&hl=en&ip=0.0.0.0&ipbits=0&expire=1670799086&sparams=ip%2Cipbits%2Cexpire%2Cv%2Cxoaf&signature=D307EA92387D1AFAA7114DA71C3D260E4B4746BE.768A476FAE903C7BA0FA22A7490DEA99991DE422&key=yt8&lang=es&fmt=srv2"}, {"ext": "srv3", "url": "https://www.youtube.com/api/timedtext?v=MlzTET_8SQg&xoaf=5&hl=en&ip=0.0.0.0&ipbits=0&expire=1670799086&sparams=ip%2Cipbits%2Cexpire%2Cv%2Cxoaf&signature=D307EA92387D1AFAA7114DA71C3D260E4B4746BE.768A476FAE903C7BA0FA22A7490DEA99991DE422&key=yt8&lang=es&fmt=srv3"}, {"ext": "ttml", "url": "https://www.youtube.com/api/timedtext?v=MlzTET_8SQg&xoaf=5&hl=en&ip=0.0.0.0&ipbits=0&expire=1670799086&sparams=ip%2Cipbits%2Cexpire%2Cv%2Cxoaf&signature=D307EA92387D1AFAA7114DA71C3D260E4B4746BE.768A476FAE903C7BA0FA22A7490DEA99991DE422&key=yt8&lang=es&fmt=ttml"}, {"ext": "vtt", "url": "https://www.youtube.com/api/timedtext?v=MlzTET_8SQg&xoaf=5&hl=en&ip=0.0.0.0&ipbits=0&expire=1670799086&sparams=ip%2Cipbits%2Cexpire%2Cv%2Cxoaf&signature=D307EA92387D1AFAA7114DA71C3D260E4B4746BE.768A476FAE903C7BA0FA22A7490DEA99991DE422&key=yt8&lang=es&fmt=vtt"}]}, "channel": "Mot\u00f6rhead Official", "extractor": "youtube", "webpage_url_basename": "watch", "extractor_key": "Youtube", "playlist": null, "playlist_index": null, "thumbnail": "https://i.ytimg.com/vi_webp/MlzTET_8SQg/maxresdefault.webp", "display_id": "MlzTET_8SQg", "asr": 44100, "filesize": null, "format_id": "18", "format_note": "360p", "fps": 30, "height": 360, "quality": 2, "tbr": 417.611, "url": "https://rr5---sn-0opoxu-ihv6.googlevideo.com/videoplayback?expire=1670795486&ei=fvyVY9KCFsKXkway_LHwCQ&ip=189.173.225.87&id=o-ABmi8SIQqP8x1u2FH9kwFA74M54JlyN7Di6pYTfCz2sD&itag=18&source=youtube&requiressl=yes&mh=YF&mm=31%2C29&mn=sn-0opoxu-ihv6%2Csn-q4flrnlz&ms=au%2Crdu&mv=m&mvi=5&pl=24&initcwndbps=861250&vprv=1&mime=video%2Fmp4&ns=-6okoeQnFx2ykP4r2_FI8bcJ&cnr=14&ratebypass=yes&dur=317.277&lmt=1665147231346096&mt=1670773517&fvip=2&fexp=24001373%2C24007246&c=WEB&txp=5538434&n=jvvLOm9NaqGXHeKYg&sparams=expire%2Cei%2Cip%2Cid%2Citag%2Csource%2Crequiressl%2Cvprv%2Cmime%2Cns%2Ccnr%2Cratebypass%2Cdur%2Clmt&lsparams=mh%2Cmm%2Cmn%2Cms%2Cmv%2Cmvi%2Cpl%2Cinitcwndbps&lsig=AG3C_xAwRQIgL8pinscdT4OZBbrFONk_lIm1nwWA3DYfFdWaluAM278CIQDiORDBXBsWtj-QomkjPCsXNeSO4PhWV0P1NHTpmW0d3g%3D%3D&sig=AOq0QJ8wRAIgTyDcVuRX8C-kECesqNlT7eO1AZtk1znMncgbr1mReFkCIBEj_gni46zpbnHSDqtgkzVLAfYvQxKhPrOV8SmcAPQE", "width": 480, "ext": "mp4", "vcodec": "avc1.42001E", "acodec": "mp4a.40.2", "format": "18 - 480x360 (360p)", "protocol": "https", "http_headers": {"User-Agent": "Mozilla/5.0 (Windows NT 10.0; Win64; x64) AppleWebKit/537.36 (KHTML, like Gecko) Chrome/74.0.3729.92 Safari/537.36", "Accept-Charset": "ISO-8859-1,utf-8;q=0.7,*;q=0.7", "Accept": "text/html,application/xhtml+xml,application/xml;q=0.9,*/*;q=0.8", "Accept-Encoding": "gzip, deflate", "Accept-Language": "en-us,en;q=0.5"}, "fulltitle": "Mot\u00f6rhead \u2013 Overkill (Official Video)", "_filename": "Mot\u00f6rhead \u2013 Overkill (Official Video)-MlzTET_8SQg.mp4"}